makenew_python_app/__init__.py
makenew_python_app/__main__.py
makenew_python_app/app.py
makenew_python_app/dependencies.py
makenew_python_app/lifecycle.py
makenew_python_app/server/__init__.py
makenew_python_app/server/boot.py
makenew_python_app/server/config.py
makenew_python_app/server/server.py
makenew_python_app/todo.py
makenew_python_app/todo_test.py
makenew_python_app-2.20.4.dist-info/LICENSE.txt
makenew_python_app-2.20.4.dist-info/WHEEL
makenew_python_app-2.20.4.dist-info/METADATA
makenew_python_app-2.20.4.dist-info/RECORD
