Metadata-Version: 2.1
Name: makenew-python-app
Version: 2.20.4
Summary: Package skeleton for a Python app.
Home-page: https://github.com/makenew/python-app
License: MIT
Author: Evan Sosenko
Author-email: razorx@evansosenko.com
Requires-Python: >=3.10.0,<4.0.0
Classifier: License :: OSI Approved :: MIT License
Classifier: Programming Language :: Python :: 3
Classifier: Programming Language :: Python :: 3.10
Requires-Dist: pinject (>=0.14.1,<0.15.0)
Requires-Dist: pyhumps (>=3.0.2,<4.0.0)
Requires-Dist: python-rapidjson (>=1.0.0,<2.0.0)
Requires-Dist: structlog (>=22.1.0,<23.0.0)
Requires-Dist: tornado (>=6.0.4,<7.0.0)
Project-URL: Repository, https://github.com/makenew/python-app
